{
  "modules": [
    {
      "name": "logger",
      "loader": {
        "name": "native",
        "entrypoint": {
          "module.path": "..\\..\\..\\modules\\logger\\Debug\\logger.dll"
        }
      },
      "args": {
        "filename": "log.json"
      }
    },
    {
      "name": "hello_world",
      "loader": {
        "name": "native",
        "entrypoint": {
          "module.path": "..\\..\\..\\modules\\hello_world\\Debug\\hello_world.dll"
        }
      },
      "args": null
    },
    {
      "name": "coap",
      "loader": {
        "name": "native",
        "entrypoint": {
          "module.path": "C:\\Repos\\azure-iot-gateway-sdk\\build\\Debug\\COAP.dll"
        }
      },
      "args": null
    }
  ],
  "links": [
    {
      "source": "coap",
      "sink": "logger"
    }
  ]
}